warriorcli/__init__.py
warriorcli/Actions/__init__.py
warriorcli/Actions/CliActions/__init__.py
warriorcli/Actions/CliActions/cli_actions.py
warriorcli/ClassUtils/__init__.py
warriorcli/ClassUtils/ssh_utils_class.py
warriorcli/ClassUtils/WNetwork/__init__.py
warriorcli/ClassUtils/WNetwork/base_class.py
warriorcli/ClassUtils/WNetwork/connection.py
warriorcli/ClassUtils/WNetwork/diagnostics.py
warriorcli/ClassUtils/WNetwork/file_ops.py
warriorcli/ClassUtils/WNetwork/loging.py
warriorcli/ClassUtils/WNetwork/network_class.py
warriorcli/ClassUtils/WNetwork/warrior_cli_class.py
warriorcli/ProductDrivers/__init__.py
warriorcli/ProductDrivers/cli_driver.py
warriorcli/Utils/__init__.py
warriorcli/Utils/cli_Utils.py
warriorcli/Utils/list_Utils.py
warriorcli-1.0.0.dist-info/METADATA
warriorcli-1.0.0.dist-info/WHEEL
warriorcli-1.0.0.dist-info/top_level.txt
warriorcli-1.0.0.dist-info/RECORD
